UseData: True
BuildSelection: WinrateBased

BuildChoices:
    # test_123 is active if Debug: True (set via a `config.yml` file)
    test_123:
        BotName: Test
        Cycle: [BcPush]

    Random:
        BotName: RandomRace
        Cycle: [BcPush]

    Protoss:
        BotName: ProtossRace
        Cycle: [BcPush]

    Terran:
        BotName: TerranRace
        Cycle: [BcPush]

    Zerg:
        BotName: ZergRace
        Cycle: [BcPush]

Builds:
    BcPush:
        AutoSupplyAtSupply: 40
        PersistentWorker: False
        ProxyBuilder:
        - 1100 ENEMY_FOURTH STARPORT
        OpeningBuildOrder:
        - 0 SUPPLYDEPOT @ RAMP
        - 0 SCV
        - 0 SCV
        - 0 BARRACKS @ RAMP
        - 0 REFINERY
        - 0 SCV
        - 0 REFINERY
        - 0 SCV
        - 0 SCV
        - 0 ORBITAL
        - 0 MARINE
        - 0 FACTORY
        - 0 SUPPLYDEPOT @ RAMP
        - 0 SCV
        - 0 BARRACKSREACTOR
        - 0 SCV
        - 0 SCV
        - 0 ARMORY
        - 0 FACTORYTECHLAB
        - 0 STARPORT @ ENEMY_FOURTH
        - 0 SIEGETANK
        - 0 SCV
        - 0 MARINE x2
        - 0 SCV
        - 0 SUPPLYDEPOT
        - 0 FUSIONCORE
        - 0 SUPPLYDEPOT
        - 0 STARPORTTECHLAB
        - 0 SCV
        - 0 MARINE x2
        - 0 SUPPLYDEPOT
        - 0 SCV
        - 0 BATTLECRUISER

        - 0 EXPAND @ NATURAL
        - 0 STARPORT @ NATURAL
        - 0 REFINERY @ NATURAL
        - 0 REFINERY @ NATURAL
        - 0 STARPORTTECHLAB @ NATURAL

        # - 0 EXPAND @ THIRD
        # - 0 STARPORT @ THIRD
        # - 0 REFINERY @ THIRD
        # - 0 REFINERY @ THIRD
        # - 0 STARPORTTECHLAB @ THIRD

        # - 0 EXPAND @ FOURTH
        # - 0 STARPORT @ FOURTH
        # - 0 REFINERY @ FOURTH
        # - 0 REFINERY @ FOURTH
        # - 0 STARPORTTECHLAB @ FOURTH

        ArmyComposition:
        - BATTLECRUISER 14
        - MARINE 50
        - SIEGETANK 4
